odoo8_addon_l10n_be_iso20022_pain-8.0.1.0.0.99.dev4-py2.7-nspkg.pth
odoo8_addon_l10n_be_iso20022_pain-8.0.1.0.0.99.dev4.dist-info/METADATA
odoo8_addon_l10n_be_iso20022_pain-8.0.1.0.0.99.dev4.dist-info/RECORD
odoo8_addon_l10n_be_iso20022_pain-8.0.1.0.0.99.dev4.dist-info/WHEEL
odoo8_addon_l10n_be_iso20022_pain-8.0.1.0.0.99.dev4.dist-info/namespace_packages.txt
odoo8_addon_l10n_be_iso20022_pain-8.0.1.0.0.99.dev4.dist-info/top_level.txt
odoo_addons/l10n_be_iso20022_pain/README.rst
odoo_addons/l10n_be_iso20022_pain/__init__.py
odoo_addons/l10n_be_iso20022_pain/__openerp__.py
odoo_addons/l10n_be_iso20022_pain/i18n/fi.po
odoo_addons/l10n_be_iso20022_pain/i18n/l10n_be_iso20022_pain.pot
odoo_addons/l10n_be_iso20022_pain/models/__init__.py
odoo_addons/l10n_be_iso20022_pain/models/payment_line.py
odoo_addons/l10n_be_iso20022_pain/static/description/icon.png
odoo_addons/l10n_be_iso20022_pain/wizard/__init__.py
odoo_addons/l10n_be_iso20022_pain/wizard/payment_order_create.py
